{"is_source_file": true, "format": "JavaScript (React JSX)", "description": "This file defines the main React component 'App' for a notes application. It manages state, fetches notes from an API, and handles CRUD operations (create, read, update, delete) for notes. It also includes UI layout code for displaying the notes list and editor interface.", "external_files": ["./App.css"], "external_methods": ["React.useState", "React.useEffect", "fetch"], "published": ["App"], "classes": [], "methods": [{"name": "App()", "description": "Main React component for notes application, handling state and UI rendering.", "scope": "", "scopeKind": ""}, {"name": "fetchNotes", "description": "Fetches all notes from the backend API and updates component state."}, {"name": "handleSelectNote", "description": "Handles selecting a note from the list and loads it into the editor."}, {"name": "handleEditorChange", "description": "Updates the editor state as user types."}, {"name": "handleNewNote", "description": "Creates a new blank note for editing."}, {"name": "handleDeleteNote", "description": "Deletes a specified note via API call."}, {"name": "handleSave", "description": "Saves the current note, either creating or updating via API."}], "calls": ["React.useState", "React.useEffect", "fetch", "setNotes", "setSelectedNoteId", "setEditorNote", "setError", "setLoading", "setSaving", "fetchNotes", "window.confirm", "fetch", "setError", "handleDeleteNote", "setSaving", "fetch", "setSelectedNoteId", "setEditorNote", "setError", "setSaving"], "search-terms": ["React", "useState", "useEffect", "fetch", "notes API", "CRUD notes", "Note Editor", "App component", "Main React App", "notes frontend"], "state": 2, "file_id": 6, "knowledge_revision": 24, "git_revision": "c944b019744a1f8dcb38e079b4ad5e963ccfc7e4", "revision_history": [{"23": "c944b019744a1f8dcb38e079b4ad5e963ccfc7e4"}, {"24": "c944b019744a1f8dcb38e079b4ad5e963ccfc7e4"}], "ctags": [{"_type": "tag", "name": "12", "path": "/home/kavia/workspace/code-generation/simple-notes-app-61c3ee49/notes_frontend/src/App.js", "pattern": "/^              rows={12}$/", "language": "JavaScript", "kind": "field", "scope": "rows", "scopeKind": "class"}, {"_type": "tag", "name": "120", "path": "/home/kavia/workspace/code-generation/simple-notes-app-61c3ee49/notes_frontend/src/App.js", "pattern": "/^              maxLength={120}$/", "language": "JavaScript", "kind": "field", "scope": "maxLength", "scopeKind": "class"}, {"_type": "tag", "name": "App", "path": "/home/kavia/workspace/code-generation/simple-notes-app-61c3ee49/notes_frontend/src/App.js", "pattern": "/^function App() {$/", "language": "JavaScript", "kind": "function", "signature": "()"}, {"_type": "tag", "name": "accent", "path": "/home/kavia/workspace/code-generation/simple-notes-app-61c3ee49/notes_frontend/src/App.js", "pattern": "/^    accent: '#4CAF50',$/", "language": "JavaScript", "kind": "property", "scope": "App.themeColors", "scopeKind": "class"}, {"_type": "tag", "name": "background", "path": "/home/kavia/workspace/code-generation/simple-notes-app-61c3ee49/notes_frontend/src/App.js", "pattern": "/^    background: 'var(--bg-primary)',$/", "language": "JavaScript", "kind": "property", "scope": "App.themeColors", "scopeKind": "class"}, {"_type": "tag", "name": "border", "path": "/home/kavia/workspace/code-generation/simple-notes-app-61c3ee49/notes_frontend/src/App.js", "pattern": "/^    border: 'var(--border-color)',$/", "language": "JavaScript", "kind": "property", "scope": "App.themeColors", "scopeKind": "class"}, {"_type": "tag", "name": "editorNote", "path": "/home/kavia/workspace/code-generation/simple-notes-app-61c3ee49/notes_frontend/src/App.js", "pattern": "/^              value={editorNote.content}$/", "language": "JavaScript", "kind": "field", "scope": "value", "scopeKind": "class"}, {"_type": "tag", "name": "editorNote", "path": "/home/kavia/workspace/code-generation/simple-notes-app-61c3ee49/notes_frontend/src/App.js", "pattern": "/^              value={editorNote.title}$/", "language": "JavaScript", "kind": "field", "scope": "value", "scopeKind": "class"}, {"_type": "tag", "name": "handleEditorChange", "path": "/home/kavia/workspace/code-generation/simple-notes-app-61c3ee49/notes_frontend/src/App.js", "pattern": "/^              onChange={handleEditorChange}$/", "language": "JavaScript", "kind": "field", "scope": "onChange", "scopeKind": "class"}, {"_type": "tag", "name": "handleNewNote", "path": "/home/kavia/workspace/code-generation/simple-notes-app-61c3ee49/notes_frontend/src/App.js", "pattern": "/^              onClick={handleNewNote}$/", "language": "JavaScript", "kind": "field", "scope": "onClick", "scopeKind": "class"}, {"_type": "tag", "name": "noteBg", "path": "/home/kavia/workspace/code-generation/simple-notes-app-61c3ee49/notes_frontend/src/App.js", "pattern": "/^    noteBg: 'var(--bg-secondary)',$/", "language": "JavaScript", "kind": "property", "scope": "App.themeColors", "scopeKind": "class"}, {"_type": "tag", "name": "primary", "path": "/home/kavia/workspace/code-generation/simple-notes-app-61c3ee49/notes_frontend/src/App.js", "pattern": "/^    primary: '#1976D2',$/", "language": "JavaScript", "kind": "property", "scope": "App.themeColors", "scopeKind": "class"}, {"_type": "tag", "name": "saving", "path": "/home/kavia/workspace/code-generation/simple-notes-app-61c3ee49/notes_frontend/src/App.js", "pattern": "/^                disabled={saving || !selectedNoteId}$/", "language": "JavaScript", "kind": "field", "scope": "disabled", "scopeKind": "class"}, {"_type": "tag", "name": "saving", "path": "/home/kavia/workspace/code-generation/simple-notes-app-61c3ee49/notes_frontend/src/App.js", "pattern": "/^                disabled={saving}$/", "language": "JavaScript", "kind": "field", "scope": "disabled", "scopeKind": "class"}, {"_type": "tag", "name": "saving", "path": "/home/kavia/workspace/code-generation/simple-notes-app-61c3ee49/notes_frontend/src/App.js", "pattern": "/^              disabled={saving}$/", "language": "JavaScript", "kind": "field", "scope": "disabled", "scopeKind": "class"}, {"_type": "tag", "name": "secondary", "path": "/home/kavia/workspace/code-generation/simple-notes-app-61c3ee49/notes_frontend/src/App.js", "pattern": "/^    secondary: '#FFC107',$/", "language": "JavaScript", "kind": "property", "scope": "App.themeColors", "scopeKind": "class"}, {"_type": "tag", "name": "text", "path": "/home/kavia/workspace/code-generation/simple-notes-app-61c3ee49/notes_frontend/src/App.js", "pattern": "/^    text: 'var(--text-primary)'$/", "language": "JavaScript", "kind": "property", "scope": "App.themeColors", "scopeKind": "class"}, {"_type": "tag", "name": "themeColors", "path": "/home/kavia/workspace/code-generation/simple-notes-app-61c3ee49/notes_frontend/src/App.js", "pattern": "/^  const themeColors = {$/", "language": "JavaScript", "kind": "class", "scope": "App", "scopeKind": "class"}, {"_type": "tag", "name": "true", "path": "/home/kavia/workspace/code-generation/simple-notes-app-61c3ee49/notes_frontend/src/App.js", "pattern": "/^              spellCheck={true}$/", "language": "JavaScript", "kind": "field", "scope": "spellCheck", "scopeKind": "class"}], "hash": "b2852b2c475b016860dec4e833e05fa7", "format-version": 4, "code-base-name": "notes_frontend", "filename": "notes_frontend/src/App.js", "fields": [{"name": "rows={12}", "scope": "rows", "scopeKind": "class", "description": "unavailable"}, {"name": "maxLength={120}", "scope": "maxLength", "scopeKind": "class", "description": "unavailable"}, {"name": "accent: '#4CAF50',", "scope": "App.themeColors", "scopeKind": "class", "description": "unavailable"}, {"name": "background: 'var(--bg-primary)',", "scope": "App.themeColors", "scopeKind": "class", "description": "unavailable"}, {"name": "border: 'var(--border-color)',", "scope": "App.themeColors", "scopeKind": "class", "description": "unavailable"}, {"name": "value={editorNote.content}", "scope": "value", "scopeKind": "class", "description": "unavailable"}, {"name": "value={editorNote.title}", "scope": "value", "scopeKind": "class", "description": "unavailable"}, {"name": "onChange={handleEditorChange}", "scope": "onChange", "scopeKind": "class", "description": "unavailable"}, {"name": "onClick={handleNewNote}", "scope": "onClick", "scopeKind": "class", "description": "unavailable"}, {"name": "noteBg: 'var(--bg-secondary)',", "scope": "App.themeColors", "scopeKind": "class", "description": "unavailable"}, {"name": "primary: '#1976D2',", "scope": "App.themeColors", "scopeKind": "class", "description": "unavailable"}, {"name": "disabled={saving || !selectedNoteId}", "scope": "disabled", "scopeKind": "class", "description": "unavailable"}, {"name": "disabled={saving}", "scope": "disabled", "scopeKind": "class", "description": "unavailable"}, {"name": "secondary: '#FFC107',", "scope": "App.themeColors", "scopeKind": "class", "description": "unavailable"}, {"name": "text: 'var(--text-primary)'", "scope": "App.themeColors", "scopeKind": "class", "description": "unavailable"}, {"name": "spellCheck={true}", "scope": "spellCheck", "scopeKind": "class", "description": "unavailable"}]}